[{"gov": "Ibb", "question_en": "First I would like to ask you about your current situation / family situation. How would you rate it on a scale from 1 to 5?", "values": [{"answer": "It is very good", "count": 7, "pct": 4.117647058823529}, {"answer": "It's somewhat bad", "count": 46, "pct": 27.058823529411764}, {"answer": "It's somewhat good", "count": 3, "pct": 1.7647058823529411}, {"answer": "It's very bad", "count": 53, "pct": 31.176470588235293}, {"answer": "Neither bad nor good", "count": 61, "pct": 35.88235294117647}]}, {"gov": "Ibb", "question_en": "In general, what do you think about the current situation in Yemen, is it going in the right direction or in the wrong direction?", "values": [{"answer": "Don't know", "count": 13, "pct": 7.647058823529412}, {"answer": "Not in the right direction, not in the wrong direction", "count": 38, "pct": 22.35294117647059}, {"answer": "In a very bad direction", "count": 57, "pct": 33.52941176470588}, {"answer": "To some extent in a bad direction", "count": 58, "pct": 34.11764705882353}, {"answer": "To some extent in the right direction", "count": 4, "pct": 2.3529411764705883}]}, {"gov": "Ibb", "question_en": "What is your status", "values": [{"answer": "Employed", "count": 4, "pct": 2.3529411764705883}, {"answer": "I am a housewife", "count": 61, "pct": 35.88235294117647}, {"answer": "I am unemployed", "count": 17, "pct": 10.0}, {"answer": "I lost my job because it got destroyed during the war", "count": 1, "pct": 0.5882352941176471}, {"answer": "I used to go to school, but I can't go to school because of other reasons", "count": 4, "pct": 2.3529411764705883}, {"answer": "I used to go to university, but I can't go to university because of other reasons", "count": 1, "pct": 0.5882352941176471}, {"answer": "I work in my own business", "count": 26, "pct": 15.294117647058824}, {"answer": "Other", "count": 1, "pct": 0.5882352941176471}, {"answer": "School student", "count": 48, "pct": 28.235294117647058}, {"answer": "University student", "count": 7, "pct": 4.117647058823529}]}, {"gov": "Ibb", "question_en": "What are the reasons you had to stop going to school, university, vocational training or lost your job? First answer", "values": [{"answer": "Because of the bad living conditions/ to help my family", "count": 4, "pct": 80.0}, {"answer": "Because of war (displacement, stop paying salaries...etc)", "count": 1, "pct": 20.0}]}, {"gov": "Ibb", "question_en": "How much time do you spend at school/university/work/vocational training?", "values": [{"answer": "1-4 hours", "count": 17, "pct": 20.0}, {"answer": "5-8 hours", "count": 61, "pct": 71.76470588235294}, {"answer": "9-12 hours", "count": 7, "pct": 8.235294117647058}]}, {"gov": "Ibb", "question_en": "How close is the school/university/work/vocational training you attend to your house?", "values": [{"answer": "0-1 km", "count": 40, "pct": 67.79661016949152}, {"answer": "11-15 km", "count": 1, "pct": 1.694915254237288}, {"answer": "16-20 km", "count": 1, "pct": 1.694915254237288}, {"answer": "2-5 km", "count": 16, "pct": 27.11864406779661}, {"answer": "More than 20 km", "count": 1, "pct": 1.694915254237288}]}, {"gov": "Ibb", "question_en": "How do you get to your school/university/work/vocational training?", "values": [{"answer": "I take a public bus", "count": 7, "pct": 11.864406779661017}, {"answer": "I walk alone", "count": 43, "pct": 72.88135593220339}, {"answer": "I walk with my mom/dad/ relative/friend", "count": 7, "pct": 11.864406779661017}, {"answer": "Taxi", "count": 2, "pct": 3.389830508474576}]}, {"gov": "Ibb", "question_en": "In what physical condition is your school/university/work/vocational training?", "values": [{"answer": "Other", "count": 3, "pct": 5.084745762711865}, {"answer": "The building is in perfect condition", "count": 31, "pct": 52.54237288135594}, {"answer": "The building is old and needs construction", "count": 25, "pct": 42.3728813559322}]}, {"gov": "Ibb", "question_en": "On a scale ranging from 1 to 5 in which \u201c1\u201d means \u201cnot valued at all\u201d and \u201c5\u201d means \u201cvery valued\u201d, how do evaluate how you feel treated by your teachers/bosses/professors?", "values": [{"answer": "2", "count": 9, "pct": 15.254237288135593}, {"answer": "3", "count": 21, "pct": 35.59322033898305}, {"answer": "4", "count": 27, "pct": 45.76271186440678}, {"answer": "Very valued", "count": 2, "pct": 3.389830508474576}]}, {"gov": "Ibb", "question_en": "On a scale ranging from 1 to 5 in which \u201c1\u201d means \u201cnot prepared at all\u201d and \u201c5\u201d means \u201cvery prepared\u201d, how do evaluate how you feel in terms of how school/university/work/vocational training prepares you for a good future life?", "values": [{"answer": "2", "count": 11, "pct": 18.64406779661017}, {"answer": "3", "count": 33, "pct": 55.932203389830505}, {"answer": "4", "count": 12, "pct": 20.33898305084746}, {"answer": "Very prepared", "count": 3, "pct": 5.084745762711865}]}, {"gov": "Ibb", "question_en": "Please indicate whether they are provided at your school/university/work place? Girls bathrooms", "values": [{"answer": "Don't know", "count": 1, "pct": 1.694915254237288}, {"answer": "No", "count": 36, "pct": 61.016949152542374}, {"answer": "Yes", "count": 22, "pct": 37.28813559322034}]}, {"gov": "Ibb", "question_en": "Please indicate whether you think it is necessary? Girls bathrooms", "values": [{"answer": "Necessary", "count": 18, "pct": 30.508474576271187}, {"answer": "Not necessary", "count": 2, "pct": 3.389830508474576}, {"answer": "Somewhat necessary", "count": 6, "pct": 10.16949152542373}, {"answer": "Very necessary", "count": 33, "pct": 55.932203389830505}]}, {"gov": "Ibb", "question_en": "Please indicate whether they are provided at your school/university/work place? Boys bathrooms", "values": [{"answer": "No", "count": 29, "pct": 49.152542372881356}, {"answer": "Yes", "count": 30, "pct": 50.847457627118644}]}, {"gov": "Ibb", "question_en": "Please indicate whether you think it is necessary? Boys bathrooms", "values": [{"answer": "Necessary", "count": 22, "pct": 37.28813559322034}, {"answer": "Not necessary", "count": 1, "pct": 1.694915254237288}, {"answer": "Somewhat necessary", "count": 6, "pct": 10.16949152542373}, {"answer": "Very necessary", "count": 30, "pct": 50.847457627118644}]}, {"gov": "Ibb", "question_en": "Please indicate whether they are provided at your school/university/work place? Library", "values": [{"answer": "Don't know", "count": 1, "pct": 1.694915254237288}, {"answer": "No", "count": 46, "pct": 77.96610169491525}, {"answer": "Yes", "count": 12, "pct": 20.33898305084746}]}, {"gov": "Ibb", "question_en": "Please indicate whether you think it is necessary? Library", "values": [{"answer": "Don't know", "count": 1, "pct": 1.694915254237288}, {"answer": "Necessary", "count": 19, "pct": 32.20338983050847}, {"answer": "Not necessary", "count": 5, "pct": 8.47457627118644}, {"answer": "Somewhat necessary", "count": 7, "pct": 11.864406779661017}, {"answer": "Very necessary", "count": 27, "pct": 45.76271186440678}]}, {"gov": "Ibb", "question_en": "Please indicate whether they are provided at your school/university/work place? Internet", "values": [{"answer": "Don't know", "count": 1, "pct": 1.694915254237288}, {"answer": "No", "count": 56, "pct": 94.91525423728814}, {"answer": "Yes", "count": 2, "pct": 3.389830508474576}]}, {"gov": "Ibb", "question_en": "Please indicate whether you think it is necessary? Internet", "values": [{"answer": "Don't know", "count": 2, "pct": 3.389830508474576}, {"answer": "Necessary", "count": 6, "pct": 10.16949152542373}, {"answer": "Not necessary", "count": 22, "pct": 37.28813559322034}, {"answer": "Somewhat necessary", "count": 25, "pct": 42.3728813559322}, {"answer": "Very necessary", "count": 4, "pct": 6.779661016949152}]}, {"gov": "Ibb", "question_en": "How much time do you often spend at home during the daytime?", "values": [{"answer": "1-4 hours", "count": 36, "pct": 21.176470588235293}, {"answer": "13-16 hours", "count": 40, "pct": 23.52941176470588}, {"answer": "5-8 hours", "count": 48, "pct": 28.235294117647058}, {"answer": "9-12 hours", "count": 42, "pct": 24.705882352941178}, {"answer": "I spend the whole day at home", "count": 4, "pct": 2.3529411764705883}]}, {"gov": "Ibb", "question_en": "Since the beginning of the war in March 2015, do you spend more or less time at home during the daytime?", "values": [{"answer": "I spend less time at home", "count": 37, "pct": 21.764705882352942}, {"answer": "I spend more time at home", "count": 42, "pct": 24.705882352941178}, {"answer": "I spend the same amount of time at home", "count": 91, "pct": 53.529411764705884}]}, {"gov": "Ibb", "question_en": "Why do spend more time at home?", "values": [{"answer": "Because of the security situation", "count": 19, "pct": 45.23809523809524}, {"answer": "I lost my job", "count": 12, "pct": 28.57142857142857}, {"answer": "My school/university was closed, I no longer go to school/University", "count": 3, "pct": 7.142857142857142}, {"answer": "Other", "count": 8, "pct": 19.047619047619047}]}, {"gov": "Ibb", "question_en": "When you think about the extra time that you have to spend at home since the beginning of the war, what do you do most in that time?", "values": [{"answer": "I chew Qat", "count": 1, "pct": 2.380952380952381}, {"answer": "I help my mother and father/ household chores", "count": 31, "pct": 73.80952380952381}, {"answer": "I read books", "count": 2, "pct": 4.761904761904762}, {"answer": "I use social media", "count": 6, "pct": 14.285714285714285}, {"answer": "I watch television", "count": 2, "pct": 4.761904761904762}]}, {"gov": "Ibb", "question_en": "What do you do when you are outside of your home, but when you are not at work/school/university/training? First answer", "values": [{"answer": "Chew Qat", "count": 18, "pct": 10.588235294117647}, {"answer": "Go shopping/ picnicking", "count": 5, "pct": 2.941176470588235}, {"answer": "Go to mosque/ Quran lessons", "count": 12, "pct": 7.0588235294117645}, {"answer": "Help my family in activities outside of home", "count": 57, "pct": 33.52941176470588}, {"answer": "Nothing/ I only go outside when it is very necessary", "count": 1, "pct": 0.5882352941176471}, {"answer": "Other", "count": 9, "pct": 5.294117647058823}, {"answer": "Play football and other games", "count": 11, "pct": 6.470588235294119}, {"answer": "Visit relatives and friends", "count": 57, "pct": 33.52941176470588}]}, {"gov": "Ibb", "question_en": "What do you do when you are outside of your home, but when you are not at work/school/university/training? Second answer", "values": [{"answer": "Chew Qat", "count": 1, "pct": 11.11111111111111}, {"answer": "Go shopping/ picnicking", "count": 2, "pct": 22.22222222222222}, {"answer": "Help my family in activities outside of home", "count": 6, "pct": 66.66666666666666}]}, {"gov": "Ibb", "question_en": "What do you do when you are outside of your home, but when you are not at work/school/university/training? Third answer", "values": [{"answer": "lmqyl m` lSdq", "count": 1, "pct": 25.0}, {"answer": "jlb lHTb", "count": 1, "pct": 25.0}, {"answer": "jlb lHTb wlm", "count": 1, "pct": 25.0}, {"answer": "r`y lGnm", "count": 1, "pct": 25.0}]}, {"gov": "Ibb", "question_en": "Is there any infrastructure in your vicinity that provides activities for youth? Such as youth centers, billiard, playgrounds, soccer/ basketball fields?", "values": [{"answer": "No", "count": 98, "pct": 57.647058823529406}, {"answer": "Yes", "count": 72, "pct": 42.35294117647059}]}, {"gov": "Ibb", "question_en": "What kind of infrastructure is in your vicinity that provides activities for youth? First answer", "values": [{"answer": "Clubs for different kinds of sport", "count": 11, "pct": 15.277777777777779}, {"answer": "Football field", "count": 58, "pct": 80.55555555555556}, {"answer": "Other", "count": 3, "pct": 4.166666666666666}]}, {"gov": "Ibb", "question_en": "Is this infrastructure youth friendly and in a good condition?", "values": [{"answer": "Don't know", "count": 1, "pct": 1.3888888888888888}, {"answer": "No", "count": 27, "pct": 37.5}, {"answer": "Yes", "count": 44, "pct": 61.111111111111114}]}, {"gov": "Ibb", "question_en": "Have you heard of Local Council being active in your area.", "values": [{"answer": "Don't know", "count": 23, "pct": 13.529411764705882}, {"answer": "I have never heard about it", "count": 46, "pct": 27.058823529411764}, {"answer": "Yes, I heard about it", "count": 101, "pct": 59.411764705882355}]}, {"gov": "Ibb", "question_en": "According to your opinion, Is Local Council  active in your area in a positive way, active in a negative way, neither positive nor negative, not active at all?", "values": [{"answer": "Don't know", "count": 7, "pct": 6.9306930693069315}, {"answer": "Active in a negative way", "count": 33, "pct": 32.67326732673268}, {"answer": "Active in a positive way", "count": 6, "pct": 5.9405940594059405}, {"answer": "Neither positive nor negative", "count": 35, "pct": 34.65346534653465}, {"answer": "Not active at all", "count": 20, "pct": 19.801980198019802}]}, {"gov": "Ibb", "question_en": "Have you heard of Political Parties being active in your area.", "values": [{"answer": "Don't know", "count": 18, "pct": 10.588235294117647}, {"answer": "I have never heard about it", "count": 45, "pct": 26.47058823529412}, {"answer": "Yes, I heard about it", "count": 107, "pct": 62.94117647058823}]}, {"gov": "Ibb", "question_en": "According to your opinion, Are Political Parties active in your area in a positive way, active in a negative way, neither positive nor negative, not active at all?", "values": [{"answer": "Don't know", "count": 6, "pct": 5.607476635514018}, {"answer": "Active in a negative way", "count": 26, "pct": 24.299065420560748}, {"answer": "Active in a positive way", "count": 2, "pct": 1.8691588785046727}, {"answer": "Neither positive nor negative", "count": 37, "pct": 34.57943925233645}, {"answer": "Not active at all", "count": 36, "pct": 33.64485981308411}]}, {"gov": "Ibb", "question_en": "Have you heard of Police being active in your area.", "values": [{"answer": "Don't know", "count": 16, "pct": 9.411764705882353}, {"answer": "I have never heard about it", "count": 35, "pct": 20.588235294117645}, {"answer": "Yes, I heard about it", "count": 119, "pct": 70.0}]}, {"gov": "Ibb", "question_en": "According to your opinion, Is Police active in your area in a positive way, active in a negative way, neither positive nor negative, not active at all?", "values": [{"answer": "Don't know", "count": 5, "pct": 4.201680672268908}, {"answer": "Active in a negative way", "count": 18, "pct": 15.126050420168067}, {"answer": "Active in a positive way", "count": 22, "pct": 18.487394957983195}, {"answer": "Neither positive nor negative", "count": 66, "pct": 55.46218487394958}, {"answer": "Not active at all", "count": 8, "pct": 6.722689075630252}]}, {"gov": "Ibb", "question_en": "Have you heard of NGO/CSO being active in your area.", "values": [{"answer": "Don't know", "count": 33, "pct": 19.411764705882355}, {"answer": "(RF)", "count": 1, "pct": 0.5882352941176471}, {"answer": "I have never heard about it", "count": 74, "pct": 43.529411764705884}, {"answer": "Yes, I heard about it", "count": 62, "pct": 36.470588235294116}]}, {"gov": "Ibb", "question_en": "According to your opinion, Is NGO/CSO active in your area in a positive way, active in a negative way, neither positive nor negative, not active at all?", "values": [{"answer": "Don't know", "count": 8, "pct": 12.903225806451612}, {"answer": "Active in a negative way", "count": 1, "pct": 1.6129032258064515}, {"answer": "Active in a positive way", "count": 4, "pct": 6.451612903225806}, {"answer": "Neither positive nor negative", "count": 27, "pct": 43.54838709677419}, {"answer": "Not active at all", "count": 22, "pct": 35.483870967741936}]}, {"gov": "Ibb", "question_en": "Have you heard of Tribal leaders being active in your area.", "values": [{"answer": "Don't know", "count": 25, "pct": 14.705882352941178}, {"answer": "(RF)", "count": 1, "pct": 0.5882352941176471}, {"answer": "I have never heard about it", "count": 53, "pct": 31.176470588235293}, {"answer": "Yes, I heard about it", "count": 91, "pct": 53.529411764705884}]}, {"gov": "Ibb", "question_en": "According to your opinion, Are Tribal leaders active in your area in a positive way, active in a negative way, neither positive nor negative, not active at all?", "values": [{"answer": "Don't know", "count": 5, "pct": 5.4945054945054945}, {"answer": "Active in a negative way", "count": 6, "pct": 6.593406593406594}, {"answer": "Active in a positive way", "count": 24, "pct": 26.373626373626376}, {"answer": "Neither positive nor negative", "count": 53, "pct": 58.24175824175825}, {"answer": "Not active at all", "count": 3, "pct": 3.296703296703297}]}, {"gov": "Ibb", "question_en": "Have you heard of Religious groups being active in your area.", "values": [{"answer": "Don't know", "count": 27, "pct": 15.88235294117647}, {"answer": "I have never heard about it", "count": 88, "pct": 51.76470588235295}, {"answer": "Yes, I heard about it", "count": 55, "pct": 32.35294117647059}]}, {"gov": "Ibb", "question_en": "According to your opinion, Are Religious groups active in your area in a positive way, active in a negative way, neither positive nor negative, not active at all?", "values": [{"answer": "Don't know", "count": 5, "pct": 9.090909090909092}, {"answer": "Active in a negative way", "count": 1, "pct": 1.8181818181818181}, {"answer": "Active in a positive way", "count": 14, "pct": 25.454545454545453}, {"answer": "Neither positive nor negative", "count": 29, "pct": 52.72727272727272}, {"answer": "Not active at all", "count": 6, "pct": 10.909090909090908}]}, {"gov": "Ibb", "question_en": "Have you heard of Youth groups being active in your area.", "values": [{"answer": "Don't know", "count": 36, "pct": 21.176470588235293}, {"answer": "I have never heard about it", "count": 101, "pct": 59.411764705882355}, {"answer": "Yes, I heard about it", "count": 33, "pct": 19.411764705882355}]}, {"gov": "Ibb", "question_en": "According to your opinion, Are Youth groups active in your area in a positive way, active in a negative way, neither positive nor negative, not active at all?", "values": [{"answer": "Active in a negative way", "count": 1, "pct": 3.0303030303030303}, {"answer": "Active in a positive way", "count": 15, "pct": 45.45454545454545}, {"answer": "Neither positive nor negative", "count": 14, "pct": 42.42424242424242}, {"answer": "Not active at all", "count": 3, "pct": 9.090909090909092}]}, {"gov": "Ibb", "question_en": "I will read a number of statements to you, please tell me how much you agree with them. I feel valued by my parents as a member of my family", "values": [{"answer": "I agree", "count": 90, "pct": 52.94117647058824}, {"answer": "I neither agree nor disagree", "count": 28, "pct": 16.470588235294116}, {"answer": "I somewhat agree", "count": 48, "pct": 28.235294117647058}, {"answer": "I somewhat disagree", "count": 4, "pct": 2.3529411764705883}]}, {"gov": "Ibb", "question_en": "I will read a number of statements to you, please tell me how much you agree with them. My parents understand my needs and try their best to satisfy them", "values": [{"answer": "I agree", "count": 44, "pct": 25.882352941176475}, {"answer": "I neither agree nor disagree", "count": 46, "pct": 27.058823529411764}, {"answer": "I somewhat agree", "count": 69, "pct": 40.588235294117645}, {"answer": "I somewhat disagree", "count": 11, "pct": 6.470588235294119}]}, {"gov": "Ibb", "question_en": "I will read a number of statements to you, please tell me how much you agree with them. My parents give me the opportunity to communicate my needs to them", "values": [{"answer": "I agree", "count": 37, "pct": 21.764705882352942}, {"answer": "I disagree", "count": 1, "pct": 0.5882352941176471}, {"answer": "I neither agree nor disagree", "count": 45, "pct": 26.47058823529412}, {"answer": "I somewhat agree", "count": 72, "pct": 42.35294117647059}, {"answer": "I somewhat disagree", "count": 15, "pct": 8.823529411764707}]}, {"gov": "Ibb", "question_en": "I will read a number of statements to you, please tell me how much you agree with them. My parents understand my problems and help me solve them", "values": [{"answer": "I agree", "count": 40, "pct": 23.52941176470588}, {"answer": "I disagree", "count": 2, "pct": 1.1764705882352942}, {"answer": "I neither agree nor disagree", "count": 36, "pct": 21.176470588235293}, {"answer": "I somewhat agree", "count": 69, "pct": 40.588235294117645}, {"answer": "I somewhat disagree", "count": 23, "pct": 13.529411764705882}]}, {"gov": "Ibb", "question_en": "How would you describe the situation of your family since the beginning of the war in March 2015?", "values": [{"answer": "Life has become a little bit more difficult, but we are doing fine", "count": 20, "pct": 11.76470588235294}, {"answer": "We are doing fine and are not affected by the war", "count": 3, "pct": 1.7647058823529411}, {"answer": "We are not able to buy food, medicine and fuel", "count": 11, "pct": 6.470588235294119}, {"answer": "We are suffering a little bit from the increase of prices for food, medicine and fuel", "count": 52, "pct": 30.58823529411765}, {"answer": "We are suffering a lot from the increase of prices for food, medicine and fuel", "count": 84, "pct": 49.411764705882355}]}, {"gov": "Ibb", "question_en": "Please tell me if food is available or not for your family", "values": [{"answer": "Available", "count": 43, "pct": 25.294117647058822}, {"answer": "Somewhat available", "count": 77, "pct": 45.294117647058826}, {"answer": "Somewhat not available", "count": 36, "pct": 21.176470588235293}, {"answer": "Very available", "count": 14, "pct": 8.235294117647058}]}, {"gov": "Ibb", "question_en": "Please tell me if water is available or not for your family", "values": [{"answer": "Available", "count": 41, "pct": 24.11764705882353}, {"answer": "Somewhat available", "count": 59, "pct": 34.705882352941174}, {"answer": "Somewhat not available", "count": 53, "pct": 31.176470588235293}, {"answer": "Very available", "count": 17, "pct": 10.0}]}, {"gov": "Ibb", "question_en": "Please tell me if Adequate  shelter/housing is available or not for your family", "values": [{"answer": "Available", "count": 39, "pct": 22.941176470588236}, {"answer": "Not available at all", "count": 1, "pct": 0.5882352941176471}, {"answer": "Somewhat available", "count": 42, "pct": 24.705882352941178}, {"answer": "Somewhat not available", "count": 7, "pct": 4.117647058823529}, {"answer": "Very available", "count": 81, "pct": 47.647058823529406}]}, {"gov": "Ibb", "question_en": "Please tell me if Electricity is available or not for your family", "values": [{"answer": "Available", "count": 35, "pct": 20.588235294117645}, {"answer": "Not available at all", "count": 46, "pct": 27.058823529411764}, {"answer": "Somewhat available", "count": 27, "pct": 15.88235294117647}, {"answer": "Somewhat not available", "count": 60, "pct": 35.294117647058826}, {"answer": "Very available", "count": 2, "pct": 1.1764705882352942}]}, {"gov": "Ibb", "question_en": "Please tell me if Health care is available or not for your family", "values": [{"answer": "Available", "count": 31, "pct": 18.235294117647058}, {"answer": "Not available at all", "count": 35, "pct": 20.588235294117645}, {"answer": "Somewhat available", "count": 22, "pct": 12.941176470588237}, {"answer": "Somewhat not available", "count": 81, "pct": 47.647058823529406}, {"answer": "Very available", "count": 1, "pct": 0.5882352941176471}]}, {"gov": "Ibb", "question_en": "Thinking about the last year, have there been times when your family didn\u2019t have enough food for all household members?", "values": [{"answer": "Don't know", "count": 7, "pct": 4.117647058823529}, {"answer": "No", "count": 121, "pct": 71.17647058823529}, {"answer": "Yes", "count": 42, "pct": 24.705882352941178}]}, {"gov": "Ibb", "question_en": "Have your family received any assistances since the beginning of the war?", "values": [{"answer": "No", "count": 118, "pct": 69.41176470588235}, {"answer": "Yes", "count": 52, "pct": 30.58823529411765}]}, {"gov": "Ibb", "question_en": "(If yes) How many times?", "values": [{"answer": "1", "count": 19, "pct": 36.53846153846153}, {"answer": "2", "count": 21, "pct": 40.38461538461539}, {"answer": "3", "count": 11, "pct": 21.153846153846153}, {"answer": "4", "count": 1, "pct": 1.9230769230769231}]}, {"gov": "Ibb", "question_en": "What kind of assistances have you received?", "values": [{"answer": "Food", "count": 52, "pct": 100.0}]}, {"gov": "Ibb", "question_en": "Which organizations/entities provided you with those assistances? First answer", "values": [{"answer": "Don't know", "count": 12, "pct": 23.076923076923077}, {"answer": "Islamic Relief", "count": 2, "pct": 3.8461538461538463}, {"answer": "Other", "count": 28, "pct": 53.84615384615385}, {"answer": "Trader/ Benefactor", "count": 3, "pct": 5.769230769230769}, {"answer": "UNICEF", "count": 1, "pct": 1.9230769230769231}, {"answer": "World Food Programme (WFP)", "count": 6, "pct": 11.538461538461538}]}, {"gov": "Ibb", "question_en": "How much sufficient were those assistances to meet your needs?", "values": [{"answer": "2", "count": 24, "pct": 46.15384615384615}, {"answer": "3", "count": 16, "pct": 30.76923076923077}, {"answer": "4", "count": 4, "pct": 7.6923076923076925}, {"answer": "Not sufficient at all", "count": 8, "pct": 15.384615384615385}]}, {"gov": "Ibb", "question_en": "What are the most Three things that your family need? First", "values": [{"answer": "Don't know", "count": 6, "pct": 3.5294117647058822}, {"answer": "Adequate house/ Transportation", "count": 9, "pct": 5.294117647058823}, {"answer": "Electricity", "count": 23, "pct": 13.529411764705882}, {"answer": "Food", "count": 63, "pct": 37.05882352941177}, {"answer": "Job opportunities/ money", "count": 16, "pct": 9.411764705882353}, {"answer": "Medicine/ Health care", "count": 4, "pct": 2.3529411764705883}, {"answer": "None", "count": 12, "pct": 7.0588235294117645}, {"answer": "Other", "count": 10, "pct": 5.88235294117647}, {"answer": "Propane gas/ fuel", "count": 12, "pct": 7.0588235294117645}, {"answer": "Water", "count": 15, "pct": 8.823529411764707}]}, {"gov": "Ibb", "question_en": "What are the most Three things that your family need? Second", "values": [{"answer": "Adequate house/ Transportation", "count": 15, "pct": 10.48951048951049}, {"answer": "Electricity", "count": 36, "pct": 25.174825174825177}, {"answer": "Food", "count": 16, "pct": 11.188811188811188}, {"answer": "Job opportunities/ money", "count": 26, "pct": 18.181818181818183}, {"answer": "Medicine/ Health care", "count": 8, "pct": 5.594405594405594}, {"answer": "None", "count": 7, "pct": 4.895104895104895}, {"answer": "Other", "count": 4, "pct": 2.797202797202797}, {"answer": "Propane gas/ fuel", "count": 14, "pct": 9.79020979020979}, {"answer": "Water", "count": 17, "pct": 11.888111888111888}]}, {"gov": "Ibb", "question_en": "What are the most Three things that your family need? Third", "values": [{"answer": "Adequate house/ Transportation", "count": 6, "pct": 6.666666666666667}, {"answer": "Electricity", "count": 25, "pct": 27.77777777777778}, {"answer": "Food", "count": 6, "pct": 6.666666666666667}, {"answer": "Job opportunities/ money", "count": 19, "pct": 21.11111111111111}, {"answer": "Medicine/ Health care", "count": 8, "pct": 8.88888888888889}, {"answer": "Other", "count": 3, "pct": 3.3333333333333335}, {"answer": "Propane gas/ fuel", "count": 12, "pct": 13.333333333333334}, {"answer": "Water", "count": 11, "pct": 12.222222222222221}]}, {"gov": "Ibb", "question_en": "Who  are the people you consider most to be influential figures in your community?", "values": [{"answer": "Don't know", "count": 8, "pct": 4.705882352941177}, {"answer": "Aqil", "count": 99, "pct": 58.235294117647065}, {"answer": "None", "count": 5, "pct": 2.941176470588235}, {"answer": "Other", "count": 18, "pct": 10.588235294117647}, {"answer": "Political party leaders", "count": 4, "pct": 2.3529411764705883}, {"answer": "Sheikh", "count": 33, "pct": 19.411764705882355}, {"answer": "State representatives at the local councils", "count": 3, "pct": 1.7647058823529411}]}, {"gov": "Ibb", "question_en": "Are you in direct personal contact with the leaders of your community?", "values": [{"answer": "No", "count": 157, "pct": 92.3529411764706}, {"answer": "Yes", "count": 13, "pct": 7.647058823529412}]}, {"gov": "Ibb", "question_en": "How are you in direct personal contact with community leaders?", "values": [{"answer": "By telephone/ Social media", "count": 1, "pct": 7.6923076923076925}, {"answer": "Face to face/ in Qat sessions/ at mosque/ public markets/ at CL house", "count": 12, "pct": 92.3076923076923}]}, {"gov": "Ibb", "question_en": "Did you ever communicate your needs to your community leader?", "values": [{"answer": "Don't know", "count": 1, "pct": 0.5882352941176471}, {"answer": "No", "count": 143, "pct": 84.11764705882354}, {"answer": "Yes", "count": 26, "pct": 15.294117647058824}]}, {"gov": "Ibb", "question_en": "Please tell me how much you agree with (I feel valued by the members of my community)", "values": [{"answer": "I agree", "count": 20, "pct": 11.76470588235294}, {"answer": "I disagree", "count": 14, "pct": 8.235294117647058}, {"answer": "I neither agree nor disagree", "count": 46, "pct": 27.058823529411764}, {"answer": "I somewhat agree", "count": 66, "pct": 38.82352941176471}, {"answer": "I somewhat disagree", "count": 24, "pct": 14.117647058823529}]}, {"gov": "Ibb", "question_en": "Please tell me how much you agree with (Community leaders understand my needs and try their best to satisfy them)", "values": [{"answer": "Don't know", "count": 2, "pct": 1.1764705882352942}, {"answer": "I agree", "count": 1, "pct": 0.5882352941176471}, {"answer": "I disagree", "count": 39, "pct": 22.941176470588236}, {"answer": "I neither agree nor disagree", "count": 64, "pct": 37.64705882352941}, {"answer": "I somewhat agree", "count": 17, "pct": 10.0}, {"answer": "I somewhat disagree", "count": 47, "pct": 27.647058823529413}]}, {"gov": "Ibb", "question_en": "Please tell me how much you agree with (Community leaders give me the opportunity to communicate my needs to them )", "values": [{"answer": "Don't know", "count": 2, "pct": 1.1764705882352942}, {"answer": "I agree", "count": 1, "pct": 0.5882352941176471}, {"answer": "I disagree", "count": 50, "pct": 29.411764705882355}, {"answer": "I neither agree nor disagree", "count": 54, "pct": 31.76470588235294}, {"answer": "I somewhat agree", "count": 14, "pct": 8.235294117647058}, {"answer": "I somewhat disagree", "count": 49, "pct": 28.823529411764703}]}, {"gov": "Ibb", "question_en": "Please tell me how much you agree with (Community leaders understand my problems and help me solve them )", "values": [{"answer": "Don't know", "count": 1, "pct": 0.5882352941176471}, {"answer": "I disagree", "count": 55, "pct": 32.35294117647059}, {"answer": "I neither agree nor disagree", "count": 54, "pct": 31.76470588235294}, {"answer": "I somewhat agree", "count": 12, "pct": 7.0588235294117645}, {"answer": "I somewhat disagree", "count": 48, "pct": 28.235294117647058}]}, {"gov": "Ibb", "question_en": "I will list read a number of places where conflicts take place, please let me know how often conflicts take place (Conflicts within the family)", "values": [{"answer": "2", "count": 58, "pct": 34.11764705882353}, {"answer": "3", "count": 17, "pct": 10.0}, {"answer": "4", "count": 23, "pct": 13.529411764705882}, {"answer": "Never", "count": 15, "pct": 8.823529411764707}, {"answer": "Very often", "count": 57, "pct": 33.52941176470588}]}, {"gov": "Ibb", "question_en": "I will list read a number of places where conflicts take place, please let me know how often conflicts take place (Conflicts with friends)", "values": [{"answer": "2", "count": 56, "pct": 32.94117647058823}, {"answer": "3", "count": 67, "pct": 39.411764705882355}, {"answer": "4", "count": 25, "pct": 14.705882352941178}, {"answer": "Never", "count": 8, "pct": 4.705882352941177}, {"answer": "Very often", "count": 14, "pct": 8.235294117647058}]}, {"gov": "Ibb", "question_en": "I will list read a number of places where conflicts take place, please let me know how often conflicts take place (Conflicts in the neighborhood)", "values": [{"answer": "2", "count": 60, "pct": 35.294117647058826}, {"answer": "3", "count": 61, "pct": 35.88235294117647}, {"answer": "4", "count": 28, "pct": 16.470588235294116}, {"answer": "Never", "count": 2, "pct": 1.1764705882352942}, {"answer": "Very often", "count": 19, "pct": 11.176470588235295}]}, {"gov": "Ibb", "question_en": "I will list a number of reasons that can lead to conflict \"Religious Differences\" (Conflicts within the family)", "values": [{"answer": "2", "count": 21, "pct": 12.352941176470589}, {"answer": "3", "count": 16, "pct": 9.411764705882353}, {"answer": "4", "count": 17, "pct": 10.0}, {"answer": "It is not a reason for our conflicts", "count": 102, "pct": 60.0}, {"answer": "It is the most important reason for our conflicts", "count": 14, "pct": 8.235294117647058}]}, {"gov": "Ibb", "question_en": "I will list a number of reasons that can lead to conflict \"Religious Differences\" (Conflicts with friends)", "values": [{"answer": "2", "count": 37, "pct": 21.764705882352942}, {"answer": "3", "count": 43, "pct": 25.294117647058822}, {"answer": "4", "count": 20, "pct": 11.76470588235294}, {"answer": "It is not a reason for our conflicts", "count": 65, "pct": 38.23529411764706}, {"answer": "It is the most important reason for our conflicts", "count": 5, "pct": 2.941176470588235}]}, {"gov": "Ibb", "question_en": "I will list a number of reasons that can lead to conflict \"Religious Differences\" (Conflicts in the neighborhood)", "values": [{"answer": "Don't know", "count": 4, "pct": 2.3529411764705883}, {"answer": "2", "count": 45, "pct": 26.47058823529412}, {"answer": "3", "count": 42, "pct": 24.705882352941178}, {"answer": "4", "count": 26, "pct": 15.294117647058824}, {"answer": "It is not a reason for our conflicts", "count": 47, "pct": 27.647058823529413}, {"answer": "It is the most important reason for our conflicts", "count": 6, "pct": 3.5294117647058822}]}, {"gov": "Ibb", "question_en": "I will list a number of reasons that can lead to conflict \"Political Difference\" (Conflicts within the family)", "values": [{"answer": "2", "count": 46, "pct": 27.058823529411764}, {"answer": "3", "count": 30, "pct": 17.647058823529413}, {"answer": "4", "count": 16, "pct": 9.411764705882353}, {"answer": "It is not a reason for our conflicts", "count": 73, "pct": 42.94117647058823}, {"answer": "It is the most important reason for our conflicts", "count": 5, "pct": 2.941176470588235}]}, {"gov": "Ibb", "question_en": "I will list a number of reasons that can lead to conflict \"Political Difference\" (Conflicts with friends)", "values": [{"answer": "Don't know", "count": 1, "pct": 0.5882352941176471}, {"answer": "2", "count": 31, "pct": 18.235294117647058}, {"answer": "3", "count": 49, "pct": 28.823529411764703}, {"answer": "4", "count": 51, "pct": 30.0}, {"answer": "It is not a reason for our conflicts", "count": 17, "pct": 10.0}, {"answer": "It is the most important reason for our conflicts", "count": 21, "pct": 12.352941176470589}]}, {"gov": "Ibb", "question_en": "I will list a number of reasons that can lead to conflict \"Political Difference\" (Conflicts in the neighborhood)", "values": [{"answer": "Don't know", "count": 1, "pct": 0.5882352941176471}, {"answer": "2", "count": 28, "pct": 16.470588235294116}, {"answer": "3", "count": 51, "pct": 30.0}, {"answer": "4", "count": 49, "pct": 28.823529411764703}, {"answer": "It is not a reason for our conflicts", "count": 3, "pct": 1.7647058823529411}, {"answer": "It is the most important reason for our conflicts", "count": 38, "pct": 22.35294117647059}]}, {"gov": "Ibb", "question_en": "I will list a number of reasons that can lead to conflict \"Food, Fuel, Water, Medicine\" (Conflicts within the family)", "values": [{"answer": "2", "count": 49, "pct": 28.823529411764703}, {"answer": "3", "count": 40, "pct": 23.52941176470588}, {"answer": "4", "count": 30, "pct": 17.647058823529413}, {"answer": "It is not a reason for our conflicts", "count": 21, "pct": 12.352941176470589}, {"answer": "It is the most important reason for our conflicts", "count": 30, "pct": 17.647058823529413}]}, {"gov": "Ibb", "question_en": "I will list a number of reasons that can lead to conflict \"Food, Fuel, Water, Medicine\" (Conflicts with friends)", "values": [{"answer": "2", "count": 65, "pct": 38.23529411764706}, {"answer": "3", "count": 44, "pct": 25.882352941176475}, {"answer": "4", "count": 28, "pct": 16.470588235294116}, {"answer": "It is not a reason for our conflicts", "count": 25, "pct": 14.705882352941178}, {"answer": "It is the most important reason for our conflicts", "count": 8, "pct": 4.705882352941177}]}, {"gov": "Ibb", "question_en": "I will list a number of reasons that can lead to conflict \"Food, Fuel, Water, Medicine\" (Conflicts in the neighborhood)", "values": [{"answer": "2", "count": 45, "pct": 26.47058823529412}, {"answer": "3", "count": 59, "pct": 34.705882352941174}, {"answer": "4", "count": 48, "pct": 28.235294117647058}, {"answer": "It is not a reason for our conflicts", "count": 7, "pct": 4.117647058823529}, {"answer": "It is the most important reason for our conflicts", "count": 11, "pct": 6.470588235294119}]}, {"gov": "Ibb", "question_en": "I will list a number of reasons that can lead to conflict \"Money\" (Conflicts within the family)", "values": [{"answer": "2", "count": 51, "pct": 30.0}, {"answer": "3", "count": 21, "pct": 12.352941176470589}, {"answer": "4", "count": 33, "pct": 19.411764705882355}, {"answer": "It is not a reason for our conflicts", "count": 25, "pct": 14.705882352941178}, {"answer": "It is the most important reason for our conflicts", "count": 40, "pct": 23.52941176470588}]}, {"gov": "Ibb", "question_en": "I will list a number of reasons that can lead to conflict \"Money\" (Conflicts with friends)", "values": [{"answer": "Don't know", "count": 1, "pct": 0.5882352941176471}, {"answer": "2", "count": 52, "pct": 30.58823529411765}, {"answer": "3", "count": 45, "pct": 26.47058823529412}, {"answer": "4", "count": 28, "pct": 16.470588235294116}, {"answer": "It is not a reason for our conflicts", "count": 35, "pct": 20.588235294117645}, {"answer": "It is the most important reason for our conflicts", "count": 9, "pct": 5.294117647058823}]}, {"gov": "Ibb", "question_en": "I will list a number of reasons that can lead to conflict \"Money\" (Conflicts in the neighborhood)", "values": [{"answer": "2", "count": 41, "pct": 24.11764705882353}, {"answer": "3", "count": 42, "pct": 24.705882352941178}, {"answer": "4", "count": 43, "pct": 25.294117647058822}, {"answer": "It is not a reason for our conflicts", "count": 24, "pct": 14.117647058823529}, {"answer": "It is the most important reason for our conflicts", "count": 20, "pct": 11.76470588235294}]}, {"gov": "Ibb", "question_en": "How present do you think the state is within your area?", "values": [{"answer": "Don't know", "count": 1, "pct": 0.5882352941176471}, {"answer": "2", "count": 68, "pct": 40.0}, {"answer": "3", "count": 62, "pct": 36.470588235294116}, {"answer": "4", "count": 8, "pct": 4.705882352941177}, {"answer": "Not present at all", "count": 31, "pct": 18.235294117647058}]}, {"gov": "Ibb", "question_en": "Would you like the state to be more or less present or stay the same in your area?", "values": [{"answer": "Don't know", "count": 2, "pct": 1.1764705882352942}, {"answer": "Less present", "count": 7, "pct": 4.117647058823529}, {"answer": "More present", "count": 150, "pct": 88.23529411764706}, {"answer": "Stay the same", "count": 11, "pct": 6.470588235294119}]}, {"gov": "Ibb", "question_en": "According to your opinion, how available are these services and products in your area? Water", "values": [{"answer": "Hardly available", "count": 58, "pct": 34.11764705882353}, {"answer": "Not available", "count": 2, "pct": 1.1764705882352942}, {"answer": "Somewhat available", "count": 70, "pct": 41.17647058823529}, {"answer": "Very available", "count": 40, "pct": 23.52941176470588}]}, {"gov": "Ibb", "question_en": "According to your opinion, how available are these services and products in your area? Fuel", "values": [{"answer": "Hardly available", "count": 73, "pct": 42.94117647058823}, {"answer": "Not available", "count": 7, "pct": 4.117647058823529}, {"answer": "Somewhat available", "count": 78, "pct": 45.88235294117647}, {"answer": "Very available", "count": 12, "pct": 7.0588235294117645}]}, {"gov": "Ibb", "question_en": "According to your opinion, how available are these services and products in your area? Propane gas", "values": [{"answer": "Hardly available", "count": 100, "pct": 58.82352941176471}, {"answer": "Not available", "count": 3, "pct": 1.7647058823529411}, {"answer": "Somewhat available", "count": 47, "pct": 27.647058823529413}, {"answer": "Very available", "count": 20, "pct": 11.76470588235294}]}, {"gov": "Ibb", "question_en": "According to your opinion, how available are these services and products in your area? Electricity", "values": [{"answer": "Hardly available", "count": 21, "pct": 12.352941176470589}, {"answer": "I have never heard about it", "count": 7, "pct": 4.117647058823529}, {"answer": "Not available", "count": 115, "pct": 67.64705882352942}, {"answer": "Somewhat available", "count": 25, "pct": 14.705882352941178}, {"answer": "Very available", "count": 2, "pct": 1.1764705882352942}]}, {"gov": "Ibb", "question_en": "According to your opinion, how available are these services and products in your area? Health Care", "values": [{"answer": "Hardly available", "count": 77, "pct": 45.294117647058826}, {"answer": "I have never heard about it", "count": 2, "pct": 1.1764705882352942}, {"answer": "Not available", "count": 34, "pct": 20.0}, {"answer": "Somewhat available", "count": 47, "pct": 27.647058823529413}, {"answer": "Very available", "count": 10, "pct": 5.88235294117647}]}, {"gov": "Ibb", "question_en": "According to your opinion, how available are these services and products in your area? Medication", "values": [{"answer": "Hardly available", "count": 74, "pct": 43.529411764705884}, {"answer": "Not available", "count": 27, "pct": 15.88235294117647}, {"answer": "Somewhat available", "count": 57, "pct": 33.52941176470588}, {"answer": "Very available", "count": 12, "pct": 7.0588235294117645}]}, {"gov": "Ibb", "question_en": "According to your opinion, how available are these services and products in your area? Education", "values": [{"answer": "Hardly available", "count": 33, "pct": 19.411764705882355}, {"answer": "Not available", "count": 2, "pct": 1.1764705882352942}, {"answer": "Somewhat available", "count": 78, "pct": 45.88235294117647}, {"answer": "Very available", "count": 57, "pct": 33.52941176470588}]}, {"gov": "Ibb", "question_en": "According to your opinion, how available are these services and products in your area? Infrastructure repair", "values": [{"answer": "Don't know", "count": 10, "pct": 5.88235294117647}, {"answer": "Hardly available", "count": 54, "pct": 31.76470588235294}, {"answer": "I have never heard about it", "count": 20, "pct": 11.76470588235294}, {"answer": "Not available", "count": 65, "pct": 38.23529411764706}, {"answer": "Somewhat available", "count": 20, "pct": 11.76470588235294}, {"answer": "Very available", "count": 1, "pct": 0.5882352941176471}]}, {"gov": "Ibb", "question_en": "According to your opinion, how available are these services and products in your area? Hygiene products", "values": [{"answer": "Don't know", "count": 10, "pct": 5.88235294117647}, {"answer": "Hardly available", "count": 35, "pct": 20.588235294117645}, {"answer": "I have never heard about it", "count": 15, "pct": 8.823529411764707}, {"answer": "Not available", "count": 52, "pct": 30.58823529411765}, {"answer": "Somewhat available", "count": 51, "pct": 30.0}, {"answer": "Very available", "count": 7, "pct": 4.117647058823529}]}, {"gov": "Ibb", "question_en": "According to your opinion, how available are these services and products in your area? Social Services", "values": [{"answer": "Don't know", "count": 17, "pct": 10.0}, {"answer": "Hardly available", "count": 50, "pct": 29.411764705882355}, {"answer": "I have never heard about it", "count": 41, "pct": 24.11764705882353}, {"answer": "Not available", "count": 51, "pct": 30.0}, {"answer": "Somewhat available", "count": 10, "pct": 5.88235294117647}, {"answer": "Very available", "count": 1, "pct": 0.5882352941176471}]}, {"gov": "Ibb", "question_en": "According to your opinion, how available are these services and products in your area? Fruit and vegetables", "values": [{"answer": "Hardly available", "count": 14, "pct": 8.235294117647058}, {"answer": "Not available", "count": 2, "pct": 1.1764705882352942}, {"answer": "Somewhat available", "count": 69, "pct": 40.588235294117645}, {"answer": "Very available", "count": 85, "pct": 50.0}]}, {"gov": "Ibb", "question_en": "According to your opinion, how available are these services and products in your area? Rice", "values": [{"answer": "Hardly available", "count": 3, "pct": 1.7647058823529411}, {"answer": "Somewhat available", "count": 56, "pct": 32.94117647058823}, {"answer": "Very available", "count": 111, "pct": 65.29411764705883}]}, {"gov": "Ibb", "question_en": "According to your opinion, how available are these services and products in your area? Chicken", "values": [{"answer": "Hardly available", "count": 2, "pct": 1.1764705882352942}, {"answer": "Somewhat available", "count": 44, "pct": 25.882352941176475}, {"answer": "Very available", "count": 124, "pct": 72.94117647058823}]}, {"gov": "Ibb", "question_en": "According to your opinion, how available are these services and products in your area? Meat", "values": [{"answer": "Hardly available", "count": 23, "pct": 13.529411764705882}, {"answer": "Not available", "count": 3, "pct": 1.7647058823529411}, {"answer": "Somewhat available", "count": 79, "pct": 46.470588235294116}, {"answer": "Very available", "count": 65, "pct": 38.23529411764706}]}, {"gov": "Ibb", "question_en": "How do evaluate the general security situation in your area?", "values": [{"answer": "2", "count": 24, "pct": 14.117647058823529}, {"answer": "3", "count": 39, "pct": 22.941176470588236}, {"answer": "4", "count": 62, "pct": 36.470588235294116}, {"answer": "Very bad", "count": 9, "pct": 5.294117647058823}, {"answer": "Very good", "count": 36, "pct": 21.176470588235293}]}, {"gov": "Ibb", "question_en": "In your opinion, what are the main reasons behind the deterioration of security situation in your area? First", "values": [{"answer": "Don't know", "count": 5, "pct": 6.944444444444445}, {"answer": "Absence of state/ Security institutions", "count": 13, "pct": 18.055555555555554}, {"answer": "Houthi group", "count": 16, "pct": 22.22222222222222}, {"answer": "Military intervention by Arab alliance", "count": 14, "pct": 19.444444444444446}, {"answer": "Other", "count": 2, "pct": 2.7777777777777777}, {"answer": "Political and tribal differences", "count": 2, "pct": 2.7777777777777777}, {"answer": "Spread of robbery gangs/ kidnapping/ assassinations", "count": 6, "pct": 8.333333333333332}, {"answer": "Spread of weapons/ armed groups", "count": 7, "pct": 9.722222222222223}, {"answer": "War/ violent clashes", "count": 7, "pct": 9.722222222222223}]}, {"gov": "Ibb", "question_en": "In your opinion, what are the main reasons behind the deterioration of security situation in your area? Second", "values": [{"answer": "Absence of state/ Security institutions", "count": 5, "pct": 12.195121951219512}, {"answer": "Houthi group", "count": 10, "pct": 24.390243902439025}, {"answer": "Military intervention by Arab alliance", "count": 3, "pct": 7.317073170731707}, {"answer": "Other", "count": 2, "pct": 4.878048780487805}, {"answer": "Political and tribal differences", "count": 1, "pct": 2.4390243902439024}, {"answer": "Spread of robbery gangs/ kidnapping/ assassinations", "count": 5, "pct": 12.195121951219512}, {"answer": "Spread of weapons/ armed groups", "count": 11, "pct": 26.82926829268293}, {"answer": "War/ violent clashes", "count": 4, "pct": 9.75609756097561}]}, {"gov": "Ibb", "question_en": "In your opinion, what are the main reasons behind the deterioration of security situation in your area? Third", "values": [{"answer": "Houthi group", "count": 1, "pct": 25.0}, {"answer": "Military intervention by Arab alliance", "count": 1, "pct": 25.0}, {"answer": "Spread of robbery gangs/ kidnapping/ assassinations", "count": 2, "pct": 50.0}]}, {"gov": "Ibb", "question_en": "On a scale ranging from 1 to 5 in which \u201c1\u201d means \u201calways very unsafe\u201d and \u201c5\u201d means \u201calways very safe\u201d, how safe do you personally feel?", "values": [{"answer": "Always safe", "count": 60, "pct": 35.294117647058826}, {"answer": "Always unsafe", "count": 12, "pct": 7.0588235294117645}, {"answer": "Mostly safe", "count": 47, "pct": 27.647058823529413}, {"answer": "Mostly unsafe", "count": 16, "pct": 9.411764705882353}, {"answer": "Neither safe nor unsafe", "count": 35, "pct": 20.588235294117645}]}, {"gov": "Ibb", "question_en": "What is the main threat that endangers your personal security?", "values": [{"answer": "Don't know", "count": 1, "pct": 0.9090909090909091}, {"answer": "Airstrike by Arab alliance", "count": 9, "pct": 8.181818181818182}, {"answer": "Bad services and living conditions", "count": 26, "pct": 23.636363636363637}, {"answer": "Go out during the night", "count": 18, "pct": 16.363636363636363}, {"answer": "Go out without Mahram (one of family men)", "count": 11, "pct": 10.0}, {"answer": "Houthi group", "count": 4, "pct": 3.6363636363636362}, {"answer": "None", "count": 26, "pct": 23.636363636363637}, {"answer": "Other", "count": 2, "pct": 1.8181818181818181}, {"answer": "Spread of robbery groups/ kidnapping/ assassinations/ absence of state", "count": 3, "pct": 2.727272727272727}, {"answer": "Spread of weapons and armed groups", "count": 5, "pct": 4.545454545454546}, {"answer": "War/ armed clashes/ random bombings/ fires", "count": 5, "pct": 4.545454545454546}]}, {"gov": "Ibb", "question_en": "What will happen if you go out without mahram?", "values": [{"answer": "lt`rD llsrq@", "count": 1, "pct": 9.090909090909092}, {"answer": "khwf mn ltHrsh", "count": 4, "pct": 36.36363636363637}, {"answer": "khwf mn lqtl w`td ljm`t lmslH@", "count": 6, "pct": 54.54545454545454}]}, {"gov": "Ibb", "question_en": "In reality, who brings security to this area? First answer", "values": [{"answer": "Don't know", "count": 18, "pct": 10.588235294117647}, {"answer": "Aqil/ Sheikhs", "count": 48, "pct": 28.235294117647058}, {"answer": "Houthis", "count": 19, "pct": 11.176470588235295}, {"answer": "None", "count": 11, "pct": 6.470588235294119}, {"answer": "Other", "count": 3, "pct": 1.7647058823529411}, {"answer": "Police/ Security forces", "count": 9, "pct": 5.294117647058823}, {"answer": "The area citizens themselves", "count": 62, "pct": 36.470588235294116}]}, {"gov": "Ibb", "question_en": "In reality, who brings security to this area? Second answer", "values": [{"answer": "Aqil/ Sheikhs", "count": 20, "pct": 28.169014084507044}, {"answer": "Houthis", "count": 9, "pct": 12.676056338028168}, {"answer": "Police/ Security forces", "count": 7, "pct": 9.859154929577464}, {"answer": "The area citizens themselves", "count": 35, "pct": 49.29577464788733}]}, {"gov": "Ibb", "question_en": "In reality, who brings security to this area? Third answer", "values": [{"answer": "Aqil/ Sheikhs", "count": 4, "pct": 36.36363636363637}, {"answer": "Houthis", "count": 1, "pct": 9.090909090909092}, {"answer": "Police/ Security forces", "count": 1, "pct": 9.090909090909092}, {"answer": "The area citizens themselves", "count": 5, "pct": 45.45454545454545}]}, {"gov": "Ibb", "question_en": "How do evaluate your knowledge on the NDC outcomes?", "values": [{"answer": "Don't know", "count": 7, "pct": 4.117647058823529}, {"answer": "2", "count": 36, "pct": 21.176470588235293}, {"answer": "3", "count": 32, "pct": 18.823529411764707}, {"answer": "4", "count": 3, "pct": 1.7647058823529411}, {"answer": "Not aware at all", "count": 91, "pct": 53.529411764705884}, {"answer": "Very aware", "count": 1, "pct": 0.5882352941176471}]}, {"gov": "Ibb", "question_en": "What in your opinion is the most important outcome of the NDC?", "values": [{"answer": "Don't know", "count": 14, "pct": 38.88888888888889}, {"answer": "Addressing Saa'da issue/ Southern issue", "count": 2, "pct": 5.555555555555555}, {"answer": "Dividing Yemen into regions", "count": 8, "pct": 22.22222222222222}, {"answer": "Other", "count": 9, "pct": 25.0}, {"answer": "Provide job opportunities/ improving security/ health and education services", "count": 3, "pct": 8.333333333333332}]}, {"gov": "Ibb", "question_en": "How do evaluate Yemen\u2019s future if the NDC outcomes were implemented?", "values": [{"answer": "Don't know", "count": 9, "pct": 25.0}, {"answer": "2", "count": 8, "pct": 22.22222222222222}, {"answer": "3", "count": 9, "pct": 25.0}, {"answer": "4", "count": 7, "pct": 19.444444444444446}, {"answer": "Very bad", "count": 2, "pct": 5.555555555555555}, {"answer": "Very good", "count": 1, "pct": 2.7777777777777777}]}, {"gov": "Ibb", "question_en": "How much do you believe Yemen should be divided into regions?", "values": [{"answer": "Don't know", "count": 16, "pct": 9.411764705882353}, {"answer": "2", "count": 42, "pct": 24.705882352941178}, {"answer": "3", "count": 14, "pct": 8.235294117647058}, {"answer": "4", "count": 3, "pct": 1.7647058823529411}, {"answer": "I don't believe Yemen should be divided into regions", "count": 95, "pct": 55.88235294117647}]}, {"gov": "Ibb", "question_en": "How much do you believe south Yemen should be independent?", "values": [{"answer": "Don't know", "count": 5, "pct": 2.941176470588235}, {"answer": "2", "count": 37, "pct": 21.764705882352942}, {"answer": "3", "count": 15, "pct": 8.823529411764707}, {"answer": "4", "count": 3, "pct": 1.7647058823529411}, {"answer": "I don't believe south Yemen should be independent", "count": 110, "pct": 64.70588235294117}]}, {"gov": "Ibb", "question_en": "Do you have internet access?", "values": [{"answer": "No", "count": 111, "pct": 65.29411764705883}, {"answer": "Yes", "count": 59, "pct": 34.705882352941174}]}, {"gov": "Ibb", "question_en": "Where do you use the internet? On my phone", "values": [{"answer": "Yes", "count": 59, "pct": 100.0}]}, {"gov": "Ibb", "question_en": "Where do you use the internet? Other", "values": [{"answer": "Yes", "count": 1, "pct": 100.0}]}, {"gov": "Ibb", "question_en": "Where do you use the internet? Other Specify;", "values": [{"answer": "mn lshbk@ fy lmnTq@", "count": 1, "pct": 100.0}]}, {"gov": "Ibb", "question_en": "Do you have a facebook account?", "values": [{"answer": "No", "count": 19, "pct": 32.20338983050847}, {"answer": "Yes", "count": 40, "pct": 67.79661016949152}]}, {"gov": "Ibb", "question_en": "How often do you use social media?", "values": [{"answer": "2", "count": 21, "pct": 35.59322033898305}, {"answer": "3", "count": 17, "pct": 28.8135593220339}, {"answer": "4", "count": 17, "pct": 28.8135593220339}, {"answer": "I frequently use social media", "count": 4, "pct": 6.779661016949152}]}, {"gov": "Ibb", "question_en": "I use social media to inform myself about the latest news", "values": [{"answer": "2", "count": 12, "pct": 20.33898305084746}, {"answer": "3", "count": 16, "pct": 27.11864406779661}, {"answer": "4", "count": 11, "pct": 18.64406779661017}, {"answer": "I strongly agree", "count": 13, "pct": 22.033898305084744}, {"answer": "I strongly disagree", "count": 7, "pct": 11.864406779661017}]}, {"gov": "Ibb", "question_en": "I use social media to stay in contact with my friends and family", "values": [{"answer": "3", "count": 4, "pct": 6.779661016949152}, {"answer": "4", "count": 15, "pct": 25.423728813559322}, {"answer": "I strongly agree", "count": 40, "pct": 67.79661016949152}]}, {"gov": "Ibb", "question_en": "I use social media to discuss politics with my friends", "values": [{"answer": "2", "count": 15, "pct": 25.423728813559322}, {"answer": "3", "count": 13, "pct": 22.033898305084744}, {"answer": "4", "count": 5, "pct": 8.47457627118644}, {"answer": "I strongly agree", "count": 5, "pct": 8.47457627118644}, {"answer": "I strongly disagree", "count": 21, "pct": 35.59322033898305}]}, {"gov": "Ibb", "question_en": "I use social media to follow Yemeni politicians", "values": [{"answer": "2", "count": 16, "pct": 27.11864406779661}, {"answer": "3", "count": 12, "pct": 20.33898305084746}, {"answer": "4", "count": 5, "pct": 8.47457627118644}, {"answer": "I strongly agree", "count": 7, "pct": 11.864406779661017}, {"answer": "I strongly disagree", "count": 19, "pct": 32.20338983050847}]}, {"gov": "Ibb", "question_en": "I use social media to let Yemeni politicians understand what I want and need", "values": [{"answer": "2", "count": 15, "pct": 25.423728813559322}, {"answer": "3", "count": 8, "pct": 13.559322033898304}, {"answer": "4", "count": 1, "pct": 1.694915254237288}, {"answer": "I strongly agree", "count": 3, "pct": 5.084745762711865}, {"answer": "I strongly disagree", "count": 32, "pct": 54.23728813559322}]}, {"gov": "Ibb", "question_en": "I use social media to follow tribal leaders", "values": [{"answer": "2", "count": 10, "pct": 16.94915254237288}, {"answer": "3", "count": 11, "pct": 18.64406779661017}, {"answer": "4", "count": 1, "pct": 1.694915254237288}, {"answer": "I strongly agree", "count": 3, "pct": 5.084745762711865}, {"answer": "I strongly disagree", "count": 34, "pct": 57.6271186440678}]}, {"gov": "Ibb", "question_en": "I use social media to let tribal leaders understand what I want and need", "values": [{"answer": "2", "count": 12, "pct": 20.33898305084746}, {"answer": "3", "count": 9, "pct": 15.254237288135593}, {"answer": "4", "count": 2, "pct": 3.389830508474576}, {"answer": "I strongly agree", "count": 1, "pct": 1.694915254237288}, {"answer": "I strongly disagree", "count": 35, "pct": 59.32203389830508}]}, {"gov": "Ibb", "question_en": "I use social media for spreading religious messages /preaching purposes", "values": [{"answer": "2", "count": 10, "pct": 16.94915254237288}, {"answer": "3", "count": 23, "pct": 38.983050847457626}, {"answer": "4", "count": 10, "pct": 16.94915254237288}, {"answer": "I strongly agree", "count": 8, "pct": 13.559322033898304}, {"answer": "I strongly disagree", "count": 8, "pct": 13.559322033898304}]}, {"gov": "Ibb", "question_en": "I use social media to follow religious figures and preachers  and to read religious messages", "values": [{"answer": "2", "count": 10, "pct": 16.94915254237288}, {"answer": "3", "count": 24, "pct": 40.67796610169492}, {"answer": "4", "count": 10, "pct": 16.94915254237288}, {"answer": "I strongly agree", "count": 9, "pct": 15.254237288135593}, {"answer": "I strongly disagree", "count": 6, "pct": 10.16949152542373}]}, {"gov": "Ibb", "question_en": "How often do you use TV", "values": [{"answer": "At least once a week", "count": 12, "pct": 7.0588235294117645}, {"answer": "Daily", "count": 25, "pct": 14.705882352941178}, {"answer": "Less than once a week", "count": 1, "pct": 0.5882352941176471}, {"answer": "Most days of week", "count": 32, "pct": 18.823529411764707}, {"answer": "Never", "count": 100, "pct": 58.82352941176471}]}, {"gov": "Ibb", "question_en": "How often do you use Radio", "values": [{"answer": "At least once a week", "count": 6, "pct": 3.5294117647058822}, {"answer": "Daily", "count": 14, "pct": 8.235294117647058}, {"answer": "Most days of week", "count": 16, "pct": 9.411764705882353}, {"answer": "Never", "count": 134, "pct": 78.82352941176471}]}, {"gov": "Ibb", "question_en": "How often do you use Newspaper", "values": [{"answer": "Less than once a week", "count": 1, "pct": 0.5882352941176471}, {"answer": "Never", "count": 169, "pct": 99.41176470588235}]}, {"gov": "Ibb", "question_en": "Compare to the period before war, do you use TV more or less", "values": [{"answer": "Less", "count": 53, "pct": 31.176470588235293}, {"answer": "More", "count": 4, "pct": 2.3529411764705883}, {"answer": "Not applicable", "count": 100, "pct": 58.82352941176471}, {"answer": "The same", "count": 13, "pct": 7.647058823529412}]}, {"gov": "Ibb", "question_en": "Compare to the period before war, do you use Radio more or less", "values": [{"answer": "Less", "count": 11, "pct": 6.470588235294119}, {"answer": "More", "count": 14, "pct": 8.235294117647058}, {"answer": "Not applicable", "count": 134, "pct": 78.82352941176471}, {"answer": "The same", "count": 11, "pct": 6.470588235294119}]}, {"gov": "Ibb", "question_en": "Compare to the period before war, do you use Newspaper more or less", "values": [{"answer": "Less", "count": 1, "pct": 0.5882352941176471}, {"answer": "Not applicable", "count": 169, "pct": 99.41176470588235}]}, {"gov": "Ibb", "question_en": "What are the Three TV stations that you most watch? First", "values": [{"answer": "Alarabya", "count": 2, "pct": 2.857142857142857}, {"answer": "Alarabya Al Hadath TV", "count": 2, "pct": 2.857142857142857}, {"answer": "Aljazeera", "count": 3, "pct": 4.285714285714286}, {"answer": "Almaseera TV", "count": 6, "pct": 8.571428571428571}, {"answer": "MBC Action", "count": 1, "pct": 1.4285714285714286}, {"answer": "National Geographic TV", "count": 1, "pct": 1.4285714285714286}, {"answer": "Other", "count": 4, "pct": 5.714285714285714}, {"answer": "Spacetoon TV", "count": 2, "pct": 2.857142857142857}, {"answer": "Yemen Shabab TV", "count": 1, "pct": 1.4285714285714286}, {"answer": "Yemen TV (belongs to legitimate government)", "count": 9, "pct": 12.857142857142856}, {"answer": "Yemen TV (broadcasts from inside Yemen)", "count": 7, "pct": 10.0}, {"answer": "Yemen Today TV", "count": 18, "pct": 25.71428571428571}, {"answer": "Zee Aflam TV", "count": 2, "pct": 2.857142857142857}, {"answer": "al-Saeeda TV", "count": 12, "pct": 17.142857142857142}]}, {"gov": "Ibb", "question_en": "What are the Three TV stations that you most watch? Second", "values": [{"answer": "Alarabya", "count": 8, "pct": 12.698412698412698}, {"answer": "Aljazeera", "count": 3, "pct": 4.761904761904762}, {"answer": "Almaseera TV", "count": 11, "pct": 17.46031746031746}, {"answer": "Alresala TV", "count": 1, "pct": 1.5873015873015872}, {"answer": "Alsahat TV", "count": 1, "pct": 1.5873015873015872}, {"answer": "MBC1", "count": 1, "pct": 1.5873015873015872}, {"answer": "Other", "count": 5, "pct": 7.936507936507936}, {"answer": "Russiya Today TV", "count": 2, "pct": 3.1746031746031744}, {"answer": "Sheba TV", "count": 1, "pct": 1.5873015873015872}, {"answer": "Suhile TV", "count": 1, "pct": 1.5873015873015872}, {"answer": "Yemen Shabab TV", "count": 3, "pct": 4.761904761904762}, {"answer": "Yemen TV (belongs to legitimate government)", "count": 1, "pct": 1.5873015873015872}, {"answer": "Yemen TV (broadcasts from inside Yemen)", "count": 7, "pct": 11.11111111111111}, {"answer": "Yemen Today TV", "count": 8, "pct": 12.698412698412698}, {"answer": "Zee Aflam TV", "count": 1, "pct": 1.5873015873015872}, {"answer": "al-Saeeda TV", "count": 9, "pct": 14.285714285714285}]}, {"gov": "Ibb", "question_en": "What are the Three TV stations that you most watch? Third", "values": [{"answer": "4Shabab TV", "count": 1, "pct": 1.8867924528301887}, {"answer": "Alarabya", "count": 4, "pct": 7.547169811320755}, {"answer": "Alarabya Al Hadath TV", "count": 5, "pct": 9.433962264150944}, {"answer": "Aljazeera", "count": 3, "pct": 5.660377358490567}, {"answer": "Almaseera TV", "count": 4, "pct": 7.547169811320755}, {"answer": "MBC Action", "count": 1, "pct": 1.8867924528301887}, {"answer": "MBC1", "count": 1, "pct": 1.8867924528301887}, {"answer": "Other", "count": 4, "pct": 7.547169811320755}, {"answer": "Sheba TV", "count": 1, "pct": 1.8867924528301887}, {"answer": "Spacetoon TV", "count": 2, "pct": 3.7735849056603774}, {"answer": "Yemen Shabab TV", "count": 6, "pct": 11.320754716981133}, {"answer": "Yemen TV (broadcasts from inside Yemen)", "count": 4, "pct": 7.547169811320755}, {"answer": "Yemen Today TV", "count": 7, "pct": 13.20754716981132}, {"answer": "al-Saeeda TV", "count": 10, "pct": 18.867924528301888}]}, {"gov": "Ibb", "question_en": "What are the Three Radio stations that you most listen? First", "values": [{"answer": "Don't know", "count": 1, "pct": 2.7777777777777777}, {"answer": "Almaseera Radio", "count": 4, "pct": 11.11111111111111}, {"answer": "Ibb Radio", "count": 10, "pct": 27.77777777777778}, {"answer": "Sana'a Radio", "count": 18, "pct": 50.0}, {"answer": "Taiz Radio", "count": 1, "pct": 2.7777777777777777}, {"answer": "Yemen FM Radio", "count": 2, "pct": 5.555555555555555}]}, {"gov": "Ibb", "question_en": "What are the Three Radio stations that you most listen? Second", "values": [{"answer": "Ibb Radio", "count": 8, "pct": 28.57142857142857}, {"answer": "Other", "count": 1, "pct": 3.571428571428571}, {"answer": "Sana'a Radio", "count": 4, "pct": 14.285714285714285}, {"answer": "Taiz Radio", "count": 10, "pct": 35.714285714285715}, {"answer": "Yemen FM Radio", "count": 5, "pct": 17.857142857142858}]}, {"gov": "Ibb", "question_en": "What are the Three Radio stations that you most listen? Third", "values": [{"answer": "Alyemen Alyoum Radio", "count": 1, "pct": 8.333333333333332}, {"answer": "Ibb Radio", "count": 1, "pct": 8.333333333333332}, {"answer": "Other", "count": 1, "pct": 8.333333333333332}, {"answer": "Sana'a Radio", "count": 2, "pct": 16.666666666666664}, {"answer": "Taiz Radio", "count": 2, "pct": 16.666666666666664}, {"answer": "Yemen FM Radio", "count": 5, "pct": 41.66666666666667}]}]